LICENSE
MANIFEST.in
README.rst
flask_mail.py
setup.cfg
setup.py
tests.py
Flask_Mail2.egg-info/PKG-INFO
Flask_Mail2.egg-info/SOURCES.txt
Flask_Mail2.egg-info/dependency_links.txt
Flask_Mail2.egg-info/not-zip-safe
Flask_Mail2.egg-info/requires.txt
Flask_Mail2.egg-info/top_level.txt
docs/Makefile
docs/changelog.rst
docs/conf.py
docs/index.rst
docs/make.bat
docs/_static/flask-mail.jpg
docs/_static/flask-mail.png