Metadata-Version: 2.1
Name: Flask-Mail2
Version: 1.0.0
Summary: Flask extension for sending email
Home-page: https://github.com/rimvislt/flask-mail2
Author: Dan Jacob
Author-email: danjac354@gmail.com
Maintainer: Rimvydas Zilinskas
Maintainer-email: rim@rdzdirect.com
License: BSD
Platform: any
Classifier: Development Status :: 4 - Beta
Classifier: Environment :: Web Environment
Classifier: Intended Audience :: Developers
Classifier: License :: OSI Approved :: BSD License
Classifier: Operating System :: OS Independent
Classifier: Programming Language :: Python
Classifier: Topic :: Internet :: WWW/HTTP :: Dynamic Content
Classifier: Topic :: Software Development :: Libraries :: Python Modules
License-File: LICENSE
